.editorconfig
.env
.gitignore
LICENSE
MANIFEST.in
Pipfile
Pipfile.lock
README.md
azure-pipelines.yml
process.json
setup.py
tox.ini
brewblox_stepper/__init__.py
brewblox_stepper/__main__.py
brewblox_stepper/actions.py
brewblox_stepper/api.py
brewblox_stepper/conditions.py
brewblox_stepper/runner.py
brewblox_stepper/sse.py
brewblox_stepper/store.py
brewblox_stepper/utils.py
brewblox_stepper/validation.py
brewblox_stepper.egg-info/PKG-INFO
brewblox_stepper.egg-info/SOURCES.txt
brewblox_stepper.egg-info/dependency_links.txt
brewblox_stepper.egg-info/requires.txt
brewblox_stepper.egg-info/top_level.txt
config/.gitkeep
docker/.gitignore
docker/localbuild.sh
docker/amd/Dockerfile
docker/arm/Dockerfile
test/__init__.py
test/conftest.py
test/test_api.py
test/test_main.py
test/test_runner.py
test/test_sse.py
test/test_store.py
test/test_validation.py